{
  "objectInfo" : {
    "id" : "fj79zpDAhIocAl0aZJbK4p",
    "name" : "Mapping1",
    "type" : "DTEMPLATE",
    "metadata" : {
      "modelVersion" : {
        "major" : 0,
        "minor" : 0
      },
      "repoInfo" : {
        "repoHandle" : "01CP6M17000000000002"
      },
      "contextAttributes" : [ {
        "name" : "id",
        "value" : "@1"
      } ],
      "additionalInfo" : {
        "description" : "",
        "contentType" : "JSON",
        "documentState" : "VALID"
      }
    }
  },
  "dataFileExtension" : "zip",
  "updateTime" : "2024-01-18T20:01:04.002Z",
  "objectRefs" : [ {
    "id" : "l5FgGdu09y8lWSCI2yFaOC",
    "name" : "FF_Test",
    "type" : "Connection",
    "metadata" : {
      "modelVersion" : {
        "major" : 0,
        "minor" : 0
      },
      "repoInfo" : {
        "repoHandle" : "01CP6M0B000000000002"
      },
      "contextAttributes" : null,
      "additionalInfo" : {
        "description" : null,
        "contentType" : "JSON",
        "documentState" : "COMPLETE"
      }
    },
    "path" : "/SYS"
  } ]
}